{"layers": [{"layer_type": "sprite", "z": 0, "data": {"sprites": [{"opacity": 255, "scale": 1, "z": 0, "label": null, "position": [-332.0, 154.0], "rotation": 0, "filename": "data/tiles/pared.jpg", "rect": [0, 0, 64, 64]}, {"opacity": 255, "scale": 1, "z": 0, "label": null, "position": [-332.0, 218.0], "rotation": 0, "filename": "data/tiles/pared.jpg", "rect": [0, 0, 64, 64]}, {"opacity": 255, "scale": 1, "z": 0, "label": null, "position": [308.0, -166.0], "rotation": 0, "filename": "data/tiles/pared.jpg", "rect": [0, 0, 64, 64]}, {"opacity": 255, "scale": 1, "z": 0, "label": null, "position": [-332.0, 90.0], "rotation": 0, "filename": "data/tiles/pared.jpg", "rect": [0, 0, 64, 64]}, {"opacity": 255, "scale": 1, "z": 0, "label": null, "position": [-332.0, 26.0], "rotation": 0, "filename": "data/tiles/pared.jpg", "rect": [0, 0, 64, 64]}, {"opacity": 255, "scale": 1, "z": 0, "label": null, "position": [-332.0, -38.0], "rotation": 0, "filename": "data/tiles/pared.jpg", "rect": [0, 0, 64, 64]}, {"opacity": 255, "scale": 1, "z": 0, "label": null, "position": [-332.0, -102.0], "rotation": 0, "filename": "data/tiles/pared.jpg", "rect": [0, 0, 64, 64]}, {"opacity": 255, "scale": 1, "z": 0, "label": null, "position": [-332.0, -230.0], "rotation": 0, "filename": "data/tiles/pared.jpg", "rect": [0, 0, 64, 64]}, {"opacity": 255, "scale": 1, "z": 0, "label": null, "position": [-332.0, -166.0], "rotation": 0, "filename": "data/tiles/pared.jpg", "rect": [0, 0, 64, 64]}, {"opacity": 255, "scale": 1, "z": 0, "label": null, "position": [-140.0, -230.0], "rotation": 0, "filename": "data/tiles/pared.jpg", "rect": [0, 0, 64, 64]}, {"opacity": 255, "scale": 1, "z": 0, "label": null, "position": [-204.0, -230.0], "rotation": 0, "filename": "data/tiles/pared.jpg", "rect": [0, 0, 64, 64]}, {"opacity": 255, "scale": 1, "z": 0, "label": null, "position": [-76.0, -230.0], "rotation": 0, "filename": "data/tiles/pared.jpg", "rect": [0, 0, 64, 64]}, {"opacity": 255, "scale": 1, "z": 0, "label": null, "position": [-12.0, -230.0], "rotation": 0, "filename": "data/tiles/pared.jpg", "rect": [0, 0, 64, 64]}, {"opacity": 255, "scale": 1, "z": 0, "label": null, "position": [180.0, -230.0], "rotation": 0, "filename": "data/tiles/pared.jpg", "rect": [0, 0, 64, 64]}, {"opacity": 255, "scale": 1, "z": 0, "label": null, "position": [52.0, -230.0], "rotation": 0, "filename": "data/tiles/pared.jpg", "rect": [0, 0, 64, 64]}, {"opacity": 255, "scale": 1, "z": 0, "label": null, "position": [116.0, -230.0], "rotation": 0, "filename": "data/tiles/pared.jpg", "rect": [0, 0, 64, 64]}, {"opacity": 255, "scale": 1, "z": 0, "label": null, "position": [244.0, -230.0], "rotation": 0, "filename": "data/tiles/pared.jpg", "rect": [0, 0, 64, 64]}, {"opacity": 255, "scale": 1, "z": 0, "label": null, "position": [308.0, -230.0], "rotation": 0, "filename": "data/tiles/pared.jpg", "rect": [0, 0, 64, 64]}, {"opacity": 255, "scale": 1, "z": 0, "label": null, "position": [308.0, 90.0], "rotation": 0, "filename": "data/tiles/pared.jpg", "rect": [0, 0, 64, 64]}, {"opacity": 255, "scale": 1, "z": 0, "label": null, "position": [308.0, -102.0], "rotation": 0, "filename": "data/tiles/pared.jpg", "rect": [0, 0, 64, 64]}, {"opacity": 255, "scale": 1, "z": 0, "label": null, "position": [308.0, -38.0], "rotation": 0, "filename": "data/tiles/pared.jpg", "rect": [0, 0, 64, 64]}, {"opacity": 255, "scale": 1, "z": 0, "label": null, "position": [308.0, 26.0], "rotation": 0, "filename": "data/tiles/pared.jpg", "rect": [0, 0, 64, 64]}, {"opacity": 255, "scale": 1, "z": 0, "label": null, "position": [308.0, 218.0], "rotation": 0, "filename": "data/tiles/pared.jpg", "rect": [0, 0, 64, 64]}, {"opacity": 255, "scale": 1, "z": 0, "label": null, "position": [116.0, 218.0], "rotation": 0, "filename": "data/tiles/pared.jpg", "rect": [0, 0, 64, 64]}, {"opacity": 255, "scale": 1, "z": 0, "label": null, "position": [244.0, 218.0], "rotation": 0, "filename": "data/tiles/pared.jpg", "rect": [0, 0, 64, 64]}, {"opacity": 255, "scale": 1, "z": 0, "label": null, "position": [180.0, 218.0], "rotation": 0, "filename": "data/tiles/pared.jpg", "rect": [0, 0, 64, 64]}, {"opacity": 255, "scale": 1, "z": 0, "label": null, "position": [52.0, 218.0], "rotation": 0, "filename": "data/tiles/pared.jpg", "rect": [0, 0, 64, 64]}, {"opacity": 255, "scale": 1, "z": 0, "label": null, "position": [-12.0, 218.0], "rotation": 0, "filename": "data/tiles/pared.jpg", "rect": [0, 0, 64, 64]}, {"opacity": 255, "scale": 1, "z": 0, "label": null, "position": [-76.0, 218.0], "rotation": 0, "filename": "data/tiles/pared.jpg", "rect": [0, 0, 64, 64]}, {"opacity": 255, "scale": 1, "z": 0, "label": null, "position": [-140.0, 218.0], "rotation": 0, "filename": "data/tiles/pared.jpg", "rect": [0, 0, 64, 64]}, {"opacity": 255, "scale": 1, "z": 0, "label": null, "position": [-204.0, 218.0], "rotation": 0, "filename": "data/tiles/pared.jpg", "rect": [0, 0, 64, 64]}, {"opacity": 255, "scale": 1, "z": 0, "label": null, "position": [-268.0, 218.0], "rotation": 0, "filename": "data/tiles/pared.jpg", "rect": [0, 0, 64, 64]}]}, "label": "sprite layer (0)"}], "tilesdir": "data/tiles/"}
